geosdevpy/__init__.py
geosdevpy/common.py
geosdevpy/geosdevpy.py
geosdevpy-0.0.1.dist-info/licenses/LICENSE
geosdevpy-0.0.1.dist-info/METADATA
geosdevpy-0.0.1.dist-info/WHEEL
geosdevpy-0.0.1.dist-info/entry_points.txt
geosdevpy-0.0.1.dist-info/top_level.txt
geosdevpy-0.0.1.dist-info/RECORD
